flashkeras/__init__.py
flashkeras/analysing/__init__.py
flashkeras/analysing/images.py
flashkeras/analysing/models.py
flashkeras/analysing/graphs/__init__.py
flashkeras/analysing/graphs/line_graphs.py
flashkeras/data_collecting/__init__.py
flashkeras/data_collecting/datasets/__init__.py
flashkeras/data_collecting/datasets/dataframes.py
flashkeras/data_collecting/datasets/image.py
flashkeras/data_collecting/datasets/matrix_like.py
flashkeras/evaluation/FlashEvaluating.py
flashkeras/evaluation/__init__.py
flashkeras/models/FlashSequential.py
flashkeras/models/FlashTransferLearning.py
flashkeras/models/__init__.py
flashkeras/models/layers/__init__.py
flashkeras/models/layers/layers.py
flashkeras/preprocessing/FlashPreProcessing.py
flashkeras/preprocessing/__init__.py
flashkeras/preprocessing/images/FlashDataGenerator.py
flashkeras/preprocessing/images/__init__.py
flashkeras/utils/__init__.py
flashkeras/utils/filesutils.py
flashkeras/utils/kerasimports.py
flashkeras/utils/otherimports.py
flashkeras/utils/typehints.py
flashkeras-0.1.6.dist-info/METADATA
flashkeras-0.1.6.dist-info/WHEEL
flashkeras-0.1.6.dist-info/top_level.txt
flashkeras-0.1.6.dist-info/RECORD
