Metadata-Version: 2.1
Name: flashkeras
Version: 0.1.6
Summary: Package to fasten Keras manipulation and overall machine learning pipeline.
Home-page: https://github.com/diegodiasfernandes/flashkeras
Author: diego dias fernandes
Author-email: diegodiasfernandes.comp@gmail.com
Classifier: Programming Language :: Python :: 3
Classifier: Programming Language :: Python :: 3.10
Classifier: Programming Language :: Python :: 3.11
Classifier: License :: OSI Approved :: MIT License
Classifier: Operating System :: OS Independent
Requires-Python: >=3.10,<3.12
Requires-Dist: tensorflow==2.15.0
Requires-Dist: matplotlib>=3.9.2
Requires-Dist: opencv-python>=4.10.0.84
Requires-Dist: pandas>=2.2.2
Requires-Dist: scikit-learn>=1.5.1
